README.rst
setup.py
uberfare/__init__.py
uberfare/__version__.py
uberfare/cli.py
uberfare/core.py
uberfare/dump.py
uberfare/environments.py
uberfare/fields.py
uberfare.egg-info/PKG-INFO
uberfare.egg-info/SOURCES.txt
uberfare.egg-info/dependency_links.txt
uberfare.egg-info/entry_points.txt
uberfare.egg-info/requires.txt
uberfare.egg-info/top_level.txt