Metadata-Version: 1.2
Name: uberfare
Version: 0.1.0
Summary: A simple tool for periodically collecting Uber fares.
Home-page: https://github.com/BurnzZ/uberfare
Author: Kevin Lloyd Bernal
Author-email: kevinlloydbernal@gmail.com
License: MIT
Platform: UNKNOWN
Classifier: Programming Language :: Python :: 3.5
Classifier: Topic :: Scientific/Engineering :: Information Analysis
Classifier: Programming Language :: Python :: 3.4
Classifier: Intended Audience :: Developers
Classifier: Topic :: Software Development
Classifier: Programming Language :: Python
Classifier: Programming Language :: Python :: 3
Classifier: License :: OSI Approved :: MIT License
Classifier: Programming Language :: Python :: Implementation :: CPython
Classifier: Programming Language :: Python :: 3.6
Classifier: Topic :: System :: Monitoring
Classifier: Environment :: Console
Classifier: Natural Language :: English
Classifier: Development Status :: 4 - Beta
Requires-Python: ~=3.4
